{
  "post": {
    "summary": "Gather",
    "description": "Gather DTMF signals to build interactive menus.\n\nYou can pass a list of valid digits. The `Answer` command must be issued before the `gather` command.\n\n**Expected Webhooks (see [callback schema](https://developers.telnyx.com/api/call-control/gather-call#callbacks) below):**\n\n- `call.dtmf.received` (you may receive many of these webhooks)\n- `call.gather.ended`\n",
    "operationId": "GatherCall",
    "tags": [
      "Call Commands"
    ],
    "parameters": [
      {
        "$ref": "../components/parameters/CallControlId.json"
      }
    ],
    "requestBody": {
      "description": "Gather",
      "required": true,
      "content": {
        "application/json": {
          "schema": {
            "$ref": "../components/schemas/GatherRequest.json"
          }
        }
      }
    },
    "responses": {
      "200": {
        "$ref": "../components/responses/CallControlCommandResponse.json"
      },
      "default": {
        "$ref": "../components/responses/GenericErrorResponse.json"
      }
    },
    "callbacks": {
      "callDtmfReceived": {
        "{$request.body#/webhook_url}": {
          "post": {
            "summary": "Calls gather call dtmf recieved",
            "requestBody": {
              "required": true,
              "content": {
                "application/json": {
                  "schema": {
                    "$ref": "../components/schemas/CallDtmfReceivedEvent.json"
                  }
                }
              }
            },
            "responses": {
              "200": {
                "description": "The server must return an HTTP 200, otherwise we will reattempt delivery at the failover webhook URL."
              }
            }
          }
        }
      },
      "callGatherEnded": {
        "{$request.body#/webhook_url}": {
          "post": {
            "summary": "Calls gather call gather ended",
            "requestBody": {
              "required": true,
              "content": {
                "application/json": {
                  "schema": {
                    "$ref": "../components/schemas/CallGatherEndedEvent.json"
                  }
                }
              }
            },
            "responses": {
              "200": {
                "description": "The server must return an HTTP 200, otherwise we will reattempt delivery at the failover webhook URL."
              }
            }
          }
        }
      }
    },
    "x-latency-category": "interactive"
  }
}