{
  "delete": {
    "summary": "Delete stored Dialogflow Connection",
    "description": "Deletes a stored Dialogflow Connection.",
    "operationId": "DeleteDialogflowConnection",
    "tags": [
      "Dialogflow Integration"
    ],
    "parameters": [
      {
        "$ref": "../components/parameters/ConnectionIdWireless.json"
      }
    ],
    "responses": {
      "204": {
        "description": "The Dialogflow Connection for connection_id was deleted successfully."
      },
      "default": {
        "$ref": "../components/responses/GenericErrorResponse.json"
      }
    },
    "x-latency-category": "responsive"
  },
  "get": {
    "summary": "Retrieve stored Dialogflow Connection",
    "description": "Return details of the Dialogflow connection associated with the given CallControl connection.",
    "operationId": "GetDialogflowConnection",
    "tags": [
      "Dialogflow Integration"
    ],
    "parameters": [
      {
        "$ref": "../components/parameters/ConnectionIdWireless.json"
      }
    ],
    "responses": {
      "200": {
        "$ref": "../components/responses/DialogflowConnectionResponseBody.json"
      },
      "default": {
        "$ref": "../components/responses/GenericErrorResponse.json"
      }
    },
    "x-latency-category": "responsive"
  },
  "post": {
    "summary": "Create a Dialogflow Connection",
    "description": "Save Dialogflow Credentiails to Telnyx, so it can be used with other Telnyx services.",
    "operationId": "CreateDialogflowConnection",
    "tags": [
      "Dialogflow Integration"
    ],
    "parameters": [
      {
        "$ref": "../components/parameters/ConnectionIdWireless.json"
      }
    ],
    "requestBody": {
      "$ref": "../components/requestBodies/DialogflowConnectionRequest.json"
    },
    "responses": {
      "201": {
        "$ref": "../components/responses/DialogflowConnectionResponseBody.json"
      },
      "default": {
        "$ref": "../components/responses/GenericErrorResponse.json"
      }
    },
    "x-latency-category": "responsive"
  },
  "put": {
    "summary": "Update stored Dialogflow Connection",
    "description": "Updates a stored Dialogflow Connection.",
    "operationId": "UpdateDialogflowConnection",
    "tags": [
      "Dialogflow Integration"
    ],
    "parameters": [
      {
        "$ref": "../components/parameters/ConnectionIdWireless.json"
      }
    ],
    "requestBody": {
      "$ref": "../components/requestBodies/DialogflowConnectionRequest.json"
    },
    "responses": {
      "200": {
        "$ref": "../components/responses/DialogflowConnectionResponseBody.json"
      },
      "default": {
        "$ref": "../components/responses/GenericErrorResponse.json"
      }
    },
    "x-latency-category": "responsive"
  }
}