{
  "get": {
    "summary": "Retrieve a document requirement",
    "deprecated": false,
    "description": "Retrieve a document requirement record",
    "operationId": "RetrieveDocumentRequirements",
    "tags": [
      "Requirements"
    ],
    "parameters": [
      {
        "name": "id",
        "in": "path",
        "description": "Uniquely identifies the requirement_type record",
        "required": true,
        "example": "a9dad8d5-fdbd-49d7-aa23-39bb08a5ebaa",
        "schema": {
          "type": "string",
          "format": "uuid"
        }
      }
    ],
    "responses": {
      "200": {
        "description": "Successful response",
        "content": {
          "application/json": {
            "schema": {
              "type": "object",
              "properties": {
                "data": {
                  "$ref": "../components/schemas/DocReqsRequirement.json"
                }
              }
            }
          }
        }
      },
      "500": {
        "description": "Unexpected error",
        "content": {
          "application/json": {
            "schema": {
              "$ref": "../components/schemas/Errors.json"
            }
          }
        }
      }
    },
    "x-latency-category": "responsive"
  }
}