{
  "get": {
    "tags": [
      "Assistants"
    ],
    "summary": "List assistants",
    "description": "Retrieve a list of all AI Assistants configured by the user.",
    "operationId": "get_assistants_public_assistants_get",
    "responses": {
      "200": {
        "description": "Successful Response",
        "content": {
          "application/json": {
            "schema": {
              "$ref": "../components/schemas/AssistantsListData.json"
            }
          }
        }
      },
      "422": {
        "description": "Validation Error",
        "content": {
          "application/json": {
            "schema": {
              "$ref": "../components/schemas/HTTPValidationError.json"
            }
          }
        }
      }
    },
    "x-latency-category": "responsive"
  },
  "post": {
    "tags": [
      "Assistants"
    ],
    "summary": "Create an assistant",
    "description": "Create a new AI Assistant.",
    "operationId": "create_new_assistant_public_assistants_post",
    "requestBody": {
      "required": true,
      "content": {
        "application/json": {
          "schema": {
            "$ref": "../components/schemas/CreateAssistantRequest.json"
          }
        }
      }
    },
    "responses": {
      "200": {
        "description": "Successful Response",
        "content": {
          "application/json": {
            "schema": {
              "$ref": "../components/schemas/Assistant.json"
            }
          }
        }
      },
      "422": {
        "description": "Validation Error",
        "content": {
          "application/json": {
            "schema": {
              "$ref": "../components/schemas/HTTPValidationError.json"
            }
          }
        }
      }
    },
    "x-latency-category": "responsive"
  }
}